cph_imgclassification/__init__.py
cph_imgclassification/__main__.py
cph_imgclassification/imageclassification/__init__.py
cph_imgclassification/imageclassification/base.yaml
cph_imgclassification/imageclassification/callbacks.py
cph_imgclassification/imageclassification/cli.py
cph_imgclassification/imageclassification/datamodule.py
cph_imgclassification/imageclassification/dataset.py
cph_imgclassification/imageclassification/mainfittest.py
cph_imgclassification/imageclassification/modelfactory.py
cph_imgclassification/imageclassification/modelmodule.py
cph_imgclassification-0.1.3.dist-info/licenses/LICENSE
cph_imgclassification-0.1.3.dist-info/METADATA
cph_imgclassification-0.1.3.dist-info/WHEEL
cph_imgclassification-0.1.3.dist-info/entry_points.txt
cph_imgclassification-0.1.3.dist-info/top_level.txt
cph_imgclassification-0.1.3.dist-info/RECORD
